LICENSE
babelbox/__init__.py
babelbox/__main__.py
babelbox/cli.py
babelbox/integration/__init__.py
babelbox/integration/beet.py
babelbox/parser.py
babelbox/utils.py
babelbox-2.1.2.dist-info/entry_points.txt
babelbox-2.1.2.dist-info/LICENSE
babelbox-2.1.2.dist-info/WHEEL
babelbox-2.1.2.dist-info/METADATA
babelbox-2.1.2.dist-info/RECORD
