Metadata-Version: 2.1
Name: babelbox
Version: 2.1.2
Summary: A language localization generator for Minecraft
Home-page: https://github.com/OrangeUtan/babelbox
License: MIT
Keywords: minecraft,lang,csv,json,localization,translation
Author: Oran9eUtan
Author-email: Oran9eUtan@gmail.com
Requires-Python: >=3.8,<4.0
Classifier: License :: OSI Approved :: MIT License
Classifier: Programming Language :: Python :: 3
Classifier: Programming Language :: Python :: 3.8
Classifier: Programming Language :: Python :: 3.9
Requires-Dist: typer (>=0.3.2,<0.4.0)
Project-URL: Repository, https://github.com/OrangeUtan/babelbox
